{
  "collapse-filter": true,
  "search": "",
  "showTags": true,
  "showAttachments": false,
  "hideUnresolved": false,
  "showOrphans": true,
  "collapse-color-groups": true,
  "colorGroups": [],
  "collapse-display": false,
  "showArrow": false,
  "textFadeMultiplier": 0,
  "nodeSizeMultiplier": 0.993229166666667,
  "lineSizeMultiplier": 0.993229166666667,
  "collapse-forces": false,
  "centerStrength": 0.4375,
  "repelStrength": 12.0833333333333,
  "linkStrength": 1,
  "linkDistance": 250,
  "scale": 1.0534979423868334,
  "close": false
}